{
	"animations": [
		{
			"loop": false,
			"offsets": [
				2,
				0
			],
			"fps": 24,
			"anim": "idle",
			"indices": [],
			"name": "Parent Christmas Idle"
		},
		{
			"loop": false,
			"offsets": [
				-114,
				24
			],
			"fps": 24,
			"anim": "singUP",
			"indices": [],
			"name": "Parent Up Note Dad"
		},
		{
			"loop": false,
			"offsets": [
				-51,
				-49
			],
			"fps": 24,
			"anim": "singDOWN",
			"indices": [],
			"name": "Parent Down Note Dad"
		},
		{
			"loop": false,
			"offsets": [
				-30,
				16
			],
			"fps": 24,
			"anim": "singLEFT",
			"indices": [],
			"name": "Parent Left Note Dad"
		},
		{
			"loop": false,
			"offsets": [
				-1,
				-23
			],
			"fps": 24,
			"anim": "singRIGHT",
			"indices": [],
			"name": "Parent Right Note Dad"
		},
		{
			"loop": false,
			"offsets": [
				-25,
				-23
			],
			"fps": 24,
			"anim": "singRIGHT-alt",
			"indices": [],
			"name": "Parent Right Note Mom"
		},
		{
			"loop": false,
			"offsets": [
				-22,
				-27
			],
			"fps": 24,
			"anim": "singDOWN-alt",
			"indices": [],
			"name": "Parent Down Note Mom"
		},
		{
			"loop": false,
			"offsets": [
				-30,
				15
			],
			"fps": 24,
			"anim": "singLEFT-alt",
			"indices": [],
			"name": "Parent Left Note Mom"
		},
		{
			"loop": false,
			"offsets": [
				-85,
				28
			],
			"fps": 24,
			"anim": "singUP-alt",
			"indices": [],
			"name": "Parent Up Note Mom"
		}
	],
	"no_antialiasing": false,
	"image": "characters/henry-cyborg",
	"position": [
		-500,
		0
	],
	"healthicon": "henry-cyborg",
	"flip_x": false,
	"healthbar_colors": [
		225,
		225,
		225
	],
	"camera_position": [
		150,
		100
	],
	"sing_duration": 4,
	"scale": 1
}